raft_pysync/__init__.py
raft_pysync/atomic_replace.py
raft_pysync/cluster_strategy.py
raft_pysync/config.py
raft_pysync/decorators.py
raft_pysync/dns_resolver.py
raft_pysync/encryptor.py
raft_pysync/journal.py
raft_pysync/node.py
raft_pysync/pickle.py
raft_pysync/pipe_notifier.py
raft_pysync/poller.py
raft_pysync/raft_pysync_obj.py
raft_pysync/serializer.py
raft_pysync/tcp_connection.py
raft_pysync/tcp_server.py
raft_pysync/transport.py
raft_pysync/types.py
raft_pysync/utility.py
raft_pysync/version.py
raft_pysync-0.2.12.dist-info/LICENSE.txt
raft_pysync-0.2.12.dist-info/METADATA
raft_pysync-0.2.12.dist-info/WHEEL
raft_pysync-0.2.12.dist-info/top_level.txt
raft_pysync-0.2.12.dist-info/RECORD
