Metadata-Version: 2.1
Name: raft_pysync
Version: 0.2.12
Summary: A library for replicating your python class between multiple servers, based on raft protocol
Home-page: https://github.com/manudiv16/raft-pysync
Author: Manudiv16
License: MIT
Keywords: network,replication,raft,synchronization
Classifier: Topic :: System :: Networking
Classifier: Topic :: System :: Distributed Computing
Classifier: Intended Audience :: Developers
Classifier: Programming Language :: Python :: 2.7
Classifier: Programming Language :: Python :: 3.4
Classifier: Programming Language :: Python :: 3.5
Classifier: Operating System :: POSIX :: Linux
Classifier: Operating System :: MacOS :: MacOS X
Classifier: License :: OSI Approved :: MIT License
License-File: LICENSE.txt
